{
  "id": "document-pr-workflow-requirements",
  "name": "document-pr-workflow-requirements",
  "title": "Document PR workflow requirements",
  "description": "",
  "status": "completed",
  "dev_type": null,
  "scope": null,
  "package": null,
  "priority": "P2",
  "creator": "competition3",
  "assignee": "competition3",
  "createdAt": "2026-06-12",
  "completedAt": "2026-06-12",
  "branch": "docs/pr-workflow-requirements",
  "base_branch": "main",
  "worktree_path": null,
  "commit": null,
  "pr_url": null,
  "subtasks": [],
  "children": [],
  "parent": null,
  "relatedFiles": [],
  "notes": "",
  "meta": {}
}